mipasa_swarm_connector/__init__.py
mipasa_swarm_connector-1.0.2.dist-info/LICENSE
mipasa_swarm_connector-1.0.2.dist-info/METADATA
mipasa_swarm_connector-1.0.2.dist-info/WHEEL
mipasa_swarm_connector-1.0.2.dist-info/top_level.txt
mipasa_swarm_connector-1.0.2.dist-info/RECORD
