Metadata-Version: 2.1
Name: mipasa_swarm_connector
Version: 1.0.2
Summary: MiPasa connector for Swarm (BZZ) distributed storage network
Author-email: MiPasa <github@mipasa.com>
License: Apache License
Project-URL: Homepage, https://github.com/MiPasa/mipasa-swarm-connector
Project-URL: Issues, https://github.com/MiPasa/mipasa-swarm-connector/issues
Classifier: Programming Language :: Python :: 3
Classifier: License :: OSI Approved :: Apache Software License
Classifier: Operating System :: OS Independent
Requires-Python: >=3.8
License-File: LICENSE
Requires-Dist: requests >=2.31.0
Provides-Extra: pandas
Requires-Dist: pandas >=1.5.3 ; extra == 'pandas'
Provides-Extra: parquet
Requires-Dist: pyarrow >=13.0.0 ; extra == 'parquet'
Provides-Extra: parquet-fastparquet
Requires-Dist: fastparquet >=2024.2.0 ; extra == 'parquet-fastparquet'
Provides-Extra: parquet-pyarrow
Requires-Dist: pyarrow >=13.0.0 ; extra == 'parquet-pyarrow'
Provides-Extra: tests
Requires-Dist: pytest >=7.1.2 ; extra == 'tests'
Requires-Dist: pytest-mock >=3.8.2 ; extra == 'tests'
Requires-Dist: requests-mock >=1.12.1 ; extra == 'tests'
Requires-Dist: pandas >=1.5.3 ; extra == 'tests'
Requires-Dist: pyarrow >=13.0.0 ; extra == 'tests'
Requires-Dist: fastparquet >=2024.2.0 ; extra == 'tests'
